{
  "title": "Glycerol-based deep eutectic solvents for efficient and reversible iodine uptake from vapour phase",
  "doi": "10.1038/s42004-025-01575-2",
  "publication_date": "2025-06-07",
  "authors": "Motta, D., Mondahchouo, S., Nejrotti, S. et al.",
  "license": "by/4.0",
  "article_url": "https://www.nature.com/articles/s42004-025-01575-2",
  "pdf_url": "https://www.nature.com/articles/s42004-025-01575-2.pdf",
  "review_url": "https://static-content.springer.com/esm/art%3A10.1038%2Fs42004-025-01575-2/MediaObjects/42004_2025_1575_MOESM1_ESM.pdf",
  "supplementary_url": null,
  "paper_id": "s42004-025-01575-2"
}